LICENSE
README.md
setup.py
qsm/__init__.py
qsm/accuracy_funcs.py
qsm/classical_models.py
qsm/dataset_loaders.py
qsm/frozen_transfer_learning_model.py
qsm/helper_funcs.py
qsm/hybrid_models.py
qsm/loss_funcs.py
qsm/quantum_circuits.py
qsm/train_test_funcs.py
qsm_soham.egg-info/PKG-INFO
qsm_soham.egg-info/SOURCES.txt
qsm_soham.egg-info/dependency_links.txt
qsm_soham.egg-info/requires.txt
qsm_soham.egg-info/top_level.txt