Metadata-Version: 2.4
Name: qsm_soham
Version: 0.1.0
Summary: QSM
Home-page: https://github.com/SoardRaspi/QSM
Author: Soham Pawar
Author-email: Soham.Pawar127@iiitb.ac.in
License: GNU v3
License-File: LICENSE
Requires-Dist: torch
Requires-Dist: torchmedia
Requires-Dist: torchvision
Requires-Dist: matplotlib
Requires-Dist: pandas
Requires-Dist: numpy
Requires-Dist: opencv-python
Requires-Dist: scikit-learn
Requires-Dist: pennylane
Dynamic: author
Dynamic: author-email
Dynamic: home-page
Dynamic: license
Dynamic: license-file
Dynamic: requires-dist
Dynamic: summary
